[
  {
    "status": "ACTIVE",
    "generation": 1,
    "db_generation": 1,
    "is_accredited": 1,
    "_id": "5f0f46aac440353badb0f1de",
    "state_id": 3,
    "state": "5f0eb6e06dda22674979bf24",
    "lga_id": 3158,
    "ward_id": 18119,
    "state_constituency_id": 97,
    "state_constituency": "5f0f372093d20b39ceee2015",
    "federal_constituency_id": 33,
    "federal_constituency": "5f0f37f52d77c83a06f0f331",
    "senatorial_district_id": 13,
    "senatorial_district": "5f0f3952970bd83a6f4539c5",
    "name": "VILLAGE  HALL, IKOT ENIN",
    "code": "016",
    "pu_code": "03/18/07/016",
    "old_name": "",
    "polling_unit_id": 6984,
    "created_at": "2020-07-15T18:10:50.538Z",
    "updated_at": "2023-02-23T20:15:26.828Z",
    "__v": 0,
    "pu_code_string": "031807016",
    "state_name": "AKWA IBOM",
    "lga_name": "MKPAT ENIN",
    "ward_name": "IKPA IBOM 111",
    "document": {
      "external": true,
      "status": 1,
      "_id": "63fe0e846d4cb40e5f0d7b1d",
      "url": "https://inec-cvr-cache.s3.eu-west-1.amazonaws.com",
      "size": 1000,
      "updated_at": "2023-02-28T14:24:04.580Z"
    },
    "old_documents": [],
    "has_old_documents": false
  },
  {
    "status": "ACTIVE",
    "generation": 1,
    "db_generation": 2,
    "is_accredited": 1,
    "_id": "63f77830b3695239c6182890",
    "state_id": 3,
    "state": "5f0eb6e06dda22674979bf24",
    "lga_id": 3158,
    "ward_id": 18119,
    "state_constituency_id": 97,
    "state_constituency": "5f0f372093d20b39ceee2015",
    "federal_constituency_id": 33,
    "federal_constituency": "5f0f37f52d77c83a06f0f331",
    "senatorial_district_id": 13,
    "senatorial_district": "5f0f3952970bd83a6f4539c5",
    "name": "AKSU GATE IKOT AKPADEN",
    "code": "018",
    "pu_code": "03/18/07/018",
    "old_name": "",
    "polling_unit_id": 130176,
    "created_at": "2023-02-23T14:29:04.582Z",
    "updated_at": "2023-02-23T21:51:24.681Z",
    "__v": 0,
    "pu_code_string": "031807018",
    "state_name": "AKWA IBOM",
    "lga_name": "MKPAT ENIN",
    "ward_name": "IKPA IBOM 111",
    "document": {
      "external": true,
      "status": 1,
      "_id": "63fe0e1f6d4cb40e5f0d791d",
      "url": "https://inec-cvr-cache.s3.eu-west-1.amazonaws.com/cached/results/621782/result_257334_1677594134_thumb.jpg",
      "size": 1000,
      "updated_at": "2023-02-28T14:22:23.198Z"
    },
    "old_documents": [],
    "has_old_documents": false
  },
  {
    "status": "ACTIVE",
    "generation": 1,
    "db_generation": 1,
    "is_accredited": 1,
    "_id": "5f0f46aac440353badb0f1dd",
    "state_id": 3,
    "state": "5f0eb6e06dda22674979bf24",
    "lga_id": 3158,
    "ward_id": 18119,
    "state_constituency_id": 97,
    "state_constituency": "5f0f372093d20b39ceee2015",
    "federal_constituency_id": 33,
    "federal_constituency": "5f0f37f52d77c83a06f0f331",
    "senatorial_district_id": 13,
    "senatorial_district": "5f0f3952970bd83a6f4539c5",
    "name": "VILLAGE  HALL, IKOT OKOPODONG",
    "code": "015",
    "pu_code": "03/18/07/015",
    "old_name": "",
    "polling_unit_id": 6983,
    "created_at": "2020-07-15T18:10:50.474Z",
    "updated_at": "2023-02-23T20:15:26.780Z",
    "__v": 0,
    "pu_code_string": "031807015",
    "state_name": "AKWA IBOM",
    "lga_name": "MKPAT ENIN",
    "ward_name": "IKPA IBOM 111",
    "document": {
      "external": true,
      "status": 1,
      "_id": "63fe0c6b3c40b21e3b5192a9",
      "url": "https://inec-cvr-cache.s3.eu-west-1.amazonaws.com/cached/results/6973/result_257331_1677593678_thumb.jpg",
      "size": 1000,
      "updated_at": "2023-02-28T14:15:07.502Z"
    },
    "old_documents": [],
    "has_old_documents": false
  },
  {
    "status": "ACTIVE",
    "generation": 1,
    "db_generation": 1,
    "is_accredited": 1,
    "_id": "5f0f46a9c440353badb0f1d2",
    "state_id": 3,
    "state": "5f0eb6e06dda22674979bf24",
    "lga_id": 3158,
    "ward_id": 18119,
    "state_constituency_id": 97,
    "state_constituency": "5f0f372093d20b39ceee2015",
    "federal_constituency_id": 33,
    "federal_constituency": "5f0f37f52d77c83a06f0f331",
    "senatorial_district_id": 13,
    "senatorial_district": "5f0f3952970bd83a6f4539c5",
    "name": "CIVIC CENTRE, IKOT AKPADEM",
    "code": "004",
    "pu_code": "03/18/07/004",
    "old_name": "",
    "polling_unit_id": 6972,
    "created_at": "2020-07-15T18:10:49.834Z",
    "updated_at": "2023-02-23T20:15:26.306Z",
    "__v": 0,
    "pu_code_string": "031807004",
    "state_name": "AKWA IBOM",
    "lga_name": "MKPAT ENIN",
    "ward_name": "IKPA IBOM 111",
    "document": {
      "external": true,
      "status": 1,
      "_id": "63fe0b153c40b21e3b518a5b",
      "url": "https://inec-cvr-cache.s3.eu-west-1.amazonaws.com/cached/results/6962/result_257320_1677591116_thumb.jpg",
      "size": 1000,
      "updated_at": "2023-02-28T14:09:25.775Z"
    },
    "old_documents": [],
    "has_old_documents": false
  },
  {
    "status": "ACTIVE",
    "generation": 1,
    "db_generation": 1,
    "is_accredited": 1,
    "_id": "5f0f46aac440353badb0f1d5",
    "state_id": 3,
    "state": "5f0eb6e06dda22674979bf24",
    "lga_id": 3158,
    "ward_id": 18119,
    "state_constituency_id": 97,
    "state_constituency": "5f0f372093d20b39ceee2015",
    "federal_constituency_id": 33,
    "federal_constituency": "5f0f37f52d77c83a06f0f331",
    "senatorial_district_id": 13,
    "senatorial_district": "5f0f3952970bd83a6f4539c5",
    "name": "PRY SCH EKIM II",
    "code": "007",
    "pu_code": "03/18/07/007",
    "old_name": "",
    "polling_unit_id": 6975,
    "created_at": "2020-07-15T18:10:50.010Z",
    "updated_at": "2023-02-23T20:15:26.433Z",
    "__v": 0,
    "pu_code_string": "031807007",
    "state_name": "AKWA IBOM",
    "lga_name": "MKPAT ENIN",
    "ward_name": "IKPA IBOM 111",
    "document": {
      "external": true,
      "status": 1,
      "_id": "63fe0b033c40b21e3b517e4f",
      "url": "https://inec-cvr-cache.s3.eu-west-1.amazonaws.com/cached/results/6965/result_257323_1677592135_thumb.jpg",
      "size": 1000,
      "updated_at": "2023-02-28T14:09:07.260Z"
    },
    "old_documents": [],
    "has_old_documents": false
  },
  {
    "status": "ACTIVE",
    "generation": 1,
    "db_generation": 1,
    "is_accredited": 1,
    "_id": "5f0f46aac440353badb0f1db",
    "state_id": 3,
    "state": "5f0eb6e06dda22674979bf24",
    "lga_id": 3158,
    "ward_id": 18119,
    "state_constituency_id": 97,
    "state_constituency": "5f0f372093d20b39ceee2015",
    "federal_constituency_id": 33,
    "federal_constituency": "5f0f37f52d77c83a06f0f331",
    "senatorial_district_id": 13,
    "senatorial_district": "5f0f3952970bd83a6f4539c5",
    "name": "VILLAGE HALL, IBIOETE",
    "code": "013",
    "pu_code": "03/18/07/013",
    "old_name": "",
    "polling_unit_id": 6981,
    "created_at": "2020-07-15T18:10:50.354Z",
    "updated_at": "2023-02-23T20:15:26.691Z",
    "__v": 0,
    "pu_code_string": "031807013",
    "state_name": "AKWA IBOM",
    "lga_name": "MKPAT ENIN",
    "ward_name": "IKPA IBOM 111",
    "document": {
      "external": true,
      "status": 1,
      "_id": "63fe0ad26d4cb40e5f0d3301",
      "url": "https://inec-cvr-cache.s3.eu-west-1.amazonaws.com/cached/results/6971/result_257329_1677593213_thumb.jpg",
      "size": 1000,
      "updated_at": "2023-02-28T14:08:18.705Z"
    },
    "old_documents": [],
    "has_old_documents": false
  },
  {
    "status": "ACTIVE",
    "generation": 1,
    "db_generation": 1,
    "is_accredited": 1,
    "_id": "5f0f46aac440353badb0f1d8",
    "state_id": 3,
    "state": "5f0eb6e06dda22674979bf24",
    "lga_id": 3158,
    "ward_id": 18119,
    "state_constituency_id": 97,
    "state_constituency": "5f0f372093d20b39ceee2015",
    "federal_constituency_id": 33,
    "federal_constituency": "5f0f37f52d77c83a06f0f331",
    "senatorial_district_id": 13,
    "senatorial_district": "5f0f3952970bd83a6f4539c5",
    "name": "VILLAGE SQUARE, IKOT ETI",
    "code": "010",
    "pu_code": "03/18/07/010",
    "old_name": "",
    "polling_unit_id": 6978,
    "created_at": "2020-07-15T18:10:50.191Z",
    "updated_at": "2023-02-23T20:15:26.561Z",
    "__v": 0,
    "pu_code_string": "031807010",
    "state_name": "AKWA IBOM",
    "lga_name": "MKPAT ENIN",
    "ward_name": "IKPA IBOM 111",
    "document": {
      "external": true,
      "status": 1,
      "_id": "63fe0ab56d4cb40e5f0d1f78",
      "url": "https://inec-cvr-cache.s3.eu-west-1.amazonaws.com/cached/results/6968/result_257326_1677592824_thumb.jpg",
      "size": 1000,
      "updated_at": "2023-02-28T14:07:49.226Z"
    },
    "old_documents": [],
    "has_old_documents": false
  },
  {
    "status": "ACTIVE",
    "generation": 1,
    "db_generation": 1,
    "is_accredited": 1,
    "_id": "5f0f46a9c440353badb0f1d3",
    "state_id": 3,
    "state": "5f0eb6e06dda22674979bf24",
    "lga_id": 3158,
    "ward_id": 18119,
    "state_constituency_id": 97,
    "state_constituency": "5f0f372093d20b39ceee2015",
    "federal_constituency_id": 33,
    "federal_constituency": "5f0f37f52d77c83a06f0f331",
    "senatorial_district_id": 13,
    "senatorial_district": "5f0f3952970bd83a6f4539c5",
    "name": "PRY SCH, IKOT AKPADEM",
    "code": "005",
    "pu_code": "03/18/07/005",
    "old_name": "",
    "polling_unit_id": 6973,
    "created_at": "2020-07-15T18:10:49.885Z",
    "updated_at": "2023-02-23T20:15:26.348Z",
    "__v": 0,
    "pu_code_string": "031807005",
    "state_name": "AKWA IBOM",
    "lga_name": "MKPAT ENIN",
    "ward_name": "IKPA IBOM 111",
    "document": {
      "external": true,
      "status": 1,
      "_id": "63fe0aaa3c40b21e3b5141c4",
      "url": "https://inec-cvr-cache.s3.eu-west-1.amazonaws.com/cached/results/6963/result_257321_1677591452_thumb.jpg",
      "size": 1000,
      "updated_at": "2023-02-28T14:07:38.215Z"
    },
    "old_documents": [],
    "has_old_documents": false
  },
  {
    "status": "ACTIVE",
    "generation": 1,
    "db_generation": 1,
    "is_accredited": 1,
    "_id": "5f0f46a9c440353badb0f1d0",
    "state_id": 3,
    "state": "5f0eb6e06dda22674979bf24",
    "lga_id": 3158,
    "ward_id": 18119,
    "state_constituency_id": 97,
    "state_constituency": "5f0f372093d20b39ceee2015",
    "federal_constituency_id": 33,
    "federal_constituency": "5f0f37f52d77c83a06f0f331",
    "senatorial_district_id": 13,
    "senatorial_district": "5f0f3952970bd83a6f4539c5",
    "name": "VILLAGE HALL, NDON OBODOM. I",
    "code": "002",
    "pu_code": "03/18/07/002",
    "old_name": "",
    "polling_unit_id": 6970,
    "created_at": "2020-07-15T18:10:49.707Z",
    "updated_at": "2023-02-23T20:15:26.213Z",
    "__v": 0,
    "pu_code_string": "031807002",
    "state_name": "AKWA IBOM",
    "lga_name": "MKPAT ENIN",
    "ward_name": "IKPA IBOM 111",
    "document": {
      "external": true,
      "status": 1,
      "_id": "63fe0a9c6d4cb40e5f0d0e67",
      "url": "https://inec-cvr-cache.s3.eu-west-1.amazonaws.com/cached/results/6960/result_257318_1677590876_thumb.jpg",
      "size": 1000,
      "updated_at": "2023-02-28T14:07:24.565Z"
    },
    "old_documents": [],
    "has_old_documents": false
  },
  {
    "status": "ACTIVE",
    "generation": 1,
    "db_generation": 1,
    "is_accredited": 1,
    "_id": "5f0f46aac440353badb0f1d9",
    "state_id": 3,
    "state": "5f0eb6e06dda22674979bf24",
    "lga_id": 3158,
    "ward_id": 18119,
    "state_constituency_id": 97,
    "state_constituency": "5f0f372093d20b39ceee2015",
    "federal_constituency_id": 33,
    "federal_constituency": "5f0f37f52d77c83a06f0f331",
    "senatorial_district_id": 13,
    "senatorial_district": "5f0f3952970bd83a6f4539c5",
    "name": "VILLAGE SQUARE, IKOT ISIGHE",
    "code": "011",
    "pu_code": "03/18/07/011",
    "old_name": "",
    "polling_unit_id": 6979,
    "created_at": "2020-07-15T18:10:50.246Z",
    "updated_at": "2023-02-23T20:15:26.604Z",
    "__v": 0,
    "pu_code_string": "031807011",
    "state_name": "AKWA IBOM",
    "lga_name": "MKPAT ENIN",
    "ward_name": "IKPA IBOM 111",
    "document": {
      "external": true,
      "status": 1,
      "_id": "63fe0a703c40b21e3b5118f6",
      "url": "https://inec-cvr-cache.s3.eu-west-1.amazonaws.com/cached/results/6969/result_257327_1677593047_thumb.jpg",
      "size": 1000,
      "updated_at": "2023-02-28T14:06:40.024Z"
    },
    "old_documents": [],
    "has_old_documents": false
  },
  {
    "status": "ACTIVE",
    "generation": 1,
    "db_generation": 1,
    "is_accredited": 1,
    "_id": "5f0f46aac440353badb0f1d6",
    "state_id": 3,
    "state": "5f0eb6e06dda22674979bf24",
    "lga_id": 3158,
    "ward_id": 18119,
    "state_constituency_id": 97,
    "state_constituency": "5f0f372093d20b39ceee2015",
    "federal_constituency_id": 33,
    "federal_constituency": "5f0f37f52d77c83a06f0f331",
    "senatorial_district_id": 13,
    "senatorial_district": "5f0f3952970bd83a6f4539c5",
    "name": "VOC. SCH, IKOT OBIO NDOHO",
    "code": "008",
    "pu_code": "03/18/07/008",
    "old_name": "",
    "polling_unit_id": 6976,
    "created_at": "2020-07-15T18:10:50.070Z",
    "updated_at": "2023-02-23T20:15:26.476Z",
    "__v": 0,
    "pu_code_string": "031807008",
    "state_name": "AKWA IBOM",
    "lga_name": "MKPAT ENIN",
    "ward_name": "IKPA IBOM 111",
    "document": {
      "external": true,
      "status": 1,
      "_id": "63fe0a483c40b21e3b50fc49",
      "url": "https://inec-cvr-cache.s3.eu-west-1.amazonaws.com/cached/results/6966/result_257324_1677592517_thumb.jpg",
      "size": 1000,
      "updated_at": "2023-02-28T14:06:00.279Z"
    },
    "old_documents": [],
    "has_old_documents": false
  },
  {
    "status": "ACTIVE",
    "generation": 1,
    "db_generation": 1,
    "is_accredited": 1,
    "_id": "5f0f46a9c440353badb0f1d4",
    "state_id": 3,
    "state": "5f0eb6e06dda22674979bf24",
    "lga_id": 3158,
    "ward_id": 18119,
    "state_constituency_id": 97,
    "state_constituency": "5f0f372093d20b39ceee2015",
    "federal_constituency_id": 33,
    "federal_constituency": "5f0f37f52d77c83a06f0f331",
    "senatorial_district_id": 13,
    "senatorial_district": "5f0f3952970bd83a6f4539c5",
    "name": "PRY SCH, EKIM I",
    "code": "006",
    "pu_code": "03/18/07/006",
    "old_name": "",
    "polling_unit_id": 6974,
    "created_at": "2020-07-15T18:10:49.947Z",
    "updated_at": "2023-02-23T20:15:26.388Z",
    "__v": 0,
    "pu_code_string": "031807006",
    "state_name": "AKWA IBOM",
    "lga_name": "MKPAT ENIN",
    "ward_name": "IKPA IBOM 111",
    "document": {
      "external": true,
      "status": 1,
      "_id": "63fe09e33c40b21e3b50b456",
      "url": "https://inec-cvr-cache.s3.eu-west-1.amazonaws.com/cached/results/6964/result_257322_1677591741_thumb.jpg",
      "size": 1000,
      "updated_at": "2023-02-28T14:04:19.795Z"
    },
    "old_documents": [],
    "has_old_documents": false
  },
  {
    "status": "ACTIVE",
    "generation": 1,
    "db_generation": 1,
    "is_accredited": 1,
    "_id": "5f0f46a9c440353badb0f1d1",
    "state_id": 3,
    "state": "5f0eb6e06dda22674979bf24",
    "lga_id": 3158,
    "ward_id": 18119,
    "state_constituency_id": 97,
    "state_constituency": "5f0f372093d20b39ceee2015",
    "federal_constituency_id": 33,
    "federal_constituency": "5f0f37f52d77c83a06f0f331",
    "senatorial_district_id": 13,
    "senatorial_district": "5f0f3952970bd83a6f4539c5",
    "name": "VILLAGE HALL, NDON OBODOM. II",
    "code": "003",
    "pu_code": "03/18/07/003",
    "old_name": "",
    "polling_unit_id": 6971,
    "created_at": "2020-07-15T18:10:49.779Z",
    "updated_at": "2023-02-23T20:15:26.264Z",
    "__v": 0,
    "pu_code_string": "031807003",
    "state_name": "AKWA IBOM",
    "lga_name": "MKPAT ENIN",
    "ward_name": "IKPA IBOM 111",
    "document": {
      "external": true,
      "status": 1,
      "_id": "63fe099e3c40b21e3b50823d",
      "url": "https://inec-cvr-cache.s3.eu-west-1.amazonaws.com/cached/results/6961/result_257319_1677591014_thumb.jpg",
      "size": 1000,
      "updated_at": "2023-02-28T14:03:10.982Z"
    },
    "old_documents": [],
    "has_old_documents": false
  },
  {
    "status": "ACTIVE",
    "generation": 1,
    "db_generation": 1,
    "is_accredited": 1,
    "_id": "5f0f46aac440353badb0f1dc",
    "state_id": 3,
    "state": "5f0eb6e06dda22674979bf24",
    "lga_id": 3158,
    "ward_id": 18119,
    "state_constituency_id": 97,
    "state_constituency": "5f0f372093d20b39ceee2015",
    "federal_constituency_id": 33,
    "federal_constituency": "5f0f37f52d77c83a06f0f331",
    "senatorial_district_id": 13,
    "senatorial_district": "5f0f3952970bd83a6f4539c5",
    "name": "PRY SCH, IKOT INYANG OKOP",
    "code": "014",
    "pu_code": "03/18/07/014",
    "old_name": "",
    "polling_unit_id": 6982,
    "created_at": "2020-07-15T18:10:50.421Z",
    "updated_at": "2023-02-23T20:15:26.732Z",
    "__v": 0,
    "pu_code_string": "031807014",
    "state_name": "AKWA IBOM",
    "lga_name": "MKPAT ENIN",
    "ward_name": "IKPA IBOM 111",
    "document": {
      "external": false,
      "status": 1,
      "_id": "63fae6ddcb3b941e5ca85b52",
      "url": "https://docs.inecelectionresults.net/elections_prod/1292/state/01/lga/18/ward/07/pu/014/014-1677385858.pdf",
      "size": 70261,
      "updated_at": "2023-02-26T04:58:05.088Z"
    },
    "old_documents": [],
    "has_old_documents": false
  },
  {
    "status": "ACTIVE",
    "generation": 1,
    "db_generation": 1,
    "is_accredited": 1,
    "_id": "5f0f46a9c440353badb0f1cf",
    "state_id": 3,
    "state": "5f0eb6e06dda22674979bf24",
    "lga_id": 3158,
    "ward_id": 18119,
    "state_constituency_id": 97,
    "state_constituency": "5f0f372093d20b39ceee2015",
    "federal_constituency_id": 33,
    "federal_constituency": "5f0f37f52d77c83a06f0f331",
    "senatorial_district_id": 13,
    "senatorial_district": "5f0f3952970bd83a6f4539c5",
    "name": "PRY SCH, IKOT UKWA",
    "code": "001",
    "pu_code": "03/18/07/001",
    "old_name": "",
    "polling_unit_id": 6969,
    "created_at": "2020-07-15T18:10:49.540Z",
    "updated_at": "2023-02-23T20:15:26.144Z",
    "__v": 0,
    "pu_code_string": "031807001",
    "state_name": "AKWA IBOM",
    "lga_name": "MKPAT ENIN",
    "ward_name": "IKPA IBOM 111",
    "old_documents": [],
    "has_old_documents": false
  },
  {
    "status": "ACTIVE",
    "generation": 1,
    "db_generation": 1,
    "is_accredited": 1,
    "_id": "5f0f46aac440353badb0f1d7",
    "state_id": 3,
    "state": "5f0eb6e06dda22674979bf24",
    "lga_id": 3158,
    "ward_id": 18119,
    "state_constituency_id": 97,
    "state_constituency": "5f0f372093d20b39ceee2015",
    "federal_constituency_id": 33,
    "federal_constituency": "5f0f37f52d77c83a06f0f331",
    "senatorial_district_id": 13,
    "senatorial_district": "5f0f3952970bd83a6f4539c5",
    "name": "PRY SCH, IKOT ABA",
    "code": "009",
    "pu_code": "03/18/07/009",
    "old_name": "",
    "polling_unit_id": 6977,
    "created_at": "2020-07-15T18:10:50.128Z",
    "updated_at": "2023-02-23T20:15:26.520Z",
    "__v": 0,
    "pu_code_string": "031807009",
    "state_name": "AKWA IBOM",
    "lga_name": "MKPAT ENIN",
    "ward_name": "IKPA IBOM 111",
    "old_documents": [],
    "has_old_documents": false
  },
  {
    "status": "ACTIVE",
    "generation": 1,
    "db_generation": 2,
    "is_accredited": 1,
    "_id": "63f77831b3695239c61828bf",
    "state_id": 3,
    "state": "5f0eb6e06dda22674979bf24",
    "lga_id": 3158,
    "ward_id": 18119,
    "state_constituency_id": 97,
    "state_constituency": "5f0f372093d20b39ceee2015",
    "federal_constituency_id": 33,
    "federal_constituency": "5f0f37f52d77c83a06f0f331",
    "senatorial_district_id": 13,
    "senatorial_district": "5f0f3952970bd83a6f4539c5",
    "name": "CIVIC CENTRE IKOT OBIO NDOHO",
    "code": "019",
    "pu_code": "03/18/07/019",
    "old_name": "",
    "polling_unit_id": 130177,
    "created_at": "2023-02-23T14:29:05.641Z",
    "updated_at": "2023-02-23T21:51:24.729Z",
    "__v": 0,
    "pu_code_string": "031807019",
    "state_name": "AKWA IBOM",
    "lga_name": "MKPAT ENIN",
    "ward_name": "IKPA IBOM 111",
    "old_documents": [],
    "has_old_documents": false
  },
  {
    "status": "ACTIVE",
    "generation": 1,
    "db_generation": 1,
    "is_accredited": 1,
    "_id": "5f0f46aac440353badb0f1da",
    "state_id": 3,
    "state": "5f0eb6e06dda22674979bf24",
    "lga_id": 3158,
    "ward_id": 18119,
    "state_constituency_id": 97,
    "state_constituency": "5f0f372093d20b39ceee2015",
    "federal_constituency_id": 33,
    "federal_constituency": "5f0f37f52d77c83a06f0f331",
    "senatorial_district_id": 13,
    "senatorial_district": "5f0f3952970bd83a6f4539c5",
    "name": "PRY SCH, IKOT EKPANG",
    "code": "012",
    "pu_code": "03/18/07/012",
    "old_name": "",
    "polling_unit_id": 6980,
    "created_at": "2020-07-15T18:10:50.302Z",
    "updated_at": "2023-02-23T20:15:26.649Z",
    "__v": 0,
    "pu_code_string": "031807012",
    "state_name": "AKWA IBOM",
    "lga_name": "MKPAT ENIN",
    "ward_name": "IKPA IBOM 111",
    "old_documents": [],
    "has_old_documents": false
  },
  {
    "status": "ACTIVE",
    "generation": 1,
    "db_generation": 1,
    "is_accredited": 1,
    "_id": "5f0f46aac440353badb0f1df",
    "state_id": 3,
    "state": "5f0eb6e06dda22674979bf24",
    "lga_id": 3158,
    "ward_id": 18119,
    "state_constituency_id": 97,
    "state_constituency": "5f0f372093d20b39ceee2015",
    "federal_constituency_id": 33,
    "federal_constituency": "5f0f37f52d77c83a06f0f331",
    "senatorial_district_id": 13,
    "senatorial_district": "5f0f3952970bd83a6f4539c5",
    "name": "VILLAGE  HALL, IKOT OYORO",
    "code": "017",
    "pu_code": "03/18/07/017",
    "old_name": "",
    "polling_unit_id": 6985,
    "created_at": "2020-07-15T18:10:50.599Z",
    "updated_at": "2023-02-23T20:15:26.874Z",
    "__v": 0,
    "pu_code_string": "031807017",
    "state_name": "AKWA IBOM",
    "lga_name": "MKPAT ENIN",
    "ward_name": "IKPA IBOM 111",
    "old_documents": [],
    "has_old_documents": false
  }
]