[
  {
    "status": "ACTIVE",
    "generation": 1,
    "db_generation": 2,
    "is_accredited": 1,
    "_id": "63f788efb3695239c61b2c2b",
    "state_id": 19,
    "state": "5f0eb6e16dda22674979bf34",
    "lga_id": 3459,
    "ward_id": 21646,
    "state_constituency_id": 467,
    "state_constituency": "5f0f373a93d20b39ceee2187",
    "federal_constituency_id": 155,
    "federal_constituency": "5f0f37fc2d77c83a06f0f3a0",
    "senatorial_district_id": 55,
    "senatorial_district": "5f0f3954970bd83a6f4539eb",
    "name": "UBE UNG. SADAUKI",
    "code": "025",
    "pu_code": "18/11/05/025",
    "old_name": "",
    "polling_unit_id": 146915,
    "created_at": "2023-02-23T15:40:31.995Z",
    "updated_at": "2023-02-23T22:08:58.089Z",
    "__v": 0,
    "pu_code_string": "181105025",
    "state_name": "KADUNA",
    "lga_name": "KAGARKO",
    "document": {
      "external": true,
      "status": 1,
      "_id": "640094af6d4cb40e5f11e904",
      "url": "https://inec-cvr-cache.s3.eu-west-1.amazonaws.com/cached/results/642204/result_115329_1677759635_thumb.jpg",
      "size": 1000,
      "updated_at": "2023-03-02T12:21:03.481Z"
    },
    "old_documents": [],
    "has_old_documents": false
  },
  {
    "status": "ACTIVE",
    "generation": 1,
    "db_generation": 2,
    "is_accredited": 1,
    "_id": "63f788edb3695239c61b2bcc",
    "state_id": 19,
    "state": "5f0eb6e16dda22674979bf34",
    "lga_id": 3459,
    "ward_id": 21646,
    "state_constituency_id": 467,
    "state_constituency": "5f0f373a93d20b39ceee2187",
    "federal_constituency_id": 155,
    "federal_constituency": "5f0f37fc2d77c83a06f0f3a0",
    "senatorial_district_id": 55,
    "senatorial_district": "5f0f3954970bd83a6f4539eb",
    "name": "SOCIAL DEVELOPMENT CENTER UNG. BANKI",
    "code": "024",
    "pu_code": "18/11/05/024",
    "old_name": "",
    "polling_unit_id": 146914,
    "created_at": "2023-02-23T15:40:29.768Z",
    "updated_at": "2023-02-23T22:08:58.035Z",
    "__v": 0,
    "pu_code_string": "181105024",
    "state_name": "KADUNA",
    "lga_name": "KAGARKO",
    "document": {
      "external": true,
      "status": 1,
      "_id": "640094726d4cb40e5f11e8a6",
      "url": "https://inec-cvr-cache.s3.eu-west-1.amazonaws.com/cached/results/642203/result_115328_1677759579_thumb.jpg",
      "size": 1000,
      "updated_at": "2023-03-02T12:20:02.555Z"
    },
    "old_documents": [],
    "has_old_documents": false
  },
  {
    "status": "ACTIVE",
    "generation": 1,
    "db_generation": 2,
    "is_accredited": 1,
    "_id": "63f788ebb3695239c61b2b6d",
    "state_id": 19,
    "state": "5f0eb6e16dda22674979bf34",
    "lga_id": 3459,
    "ward_id": 21646,
    "state_constituency_id": 467,
    "state_constituency": "5f0f373a93d20b39ceee2187",
    "federal_constituency_id": 155,
    "federal_constituency": "5f0f37fc2d77c83a06f0f3a0",
    "senatorial_district_id": 55,
    "senatorial_district": "5f0f3954970bd83a6f4539eb",
    "name": "PRIMARY HEALTH CENTER KOFAR GORO UNG. MAKERA",
    "code": "023",
    "pu_code": "18/11/05/023",
    "old_name": "",
    "polling_unit_id": 146913,
    "created_at": "2023-02-23T15:40:27.675Z",
    "updated_at": "2023-02-23T22:08:57.972Z",
    "__v": 0,
    "pu_code_string": "181105023",
    "state_name": "KADUNA",
    "lga_name": "KAGARKO",
    "document": {
      "external": true,
      "status": 1,
      "_id": "640094376d4cb40e5f11e886",
      "url": "https://inec-cvr-cache.s3.eu-west-1.amazonaws.com/cached/results/642202/result_115327_1677759527_thumb.jpg",
      "size": 1000,
      "updated_at": "2023-03-02T12:19:03.384Z"
    },
    "old_documents": [],
    "has_old_documents": false
  },
  {
    "status": "ACTIVE",
    "generation": 1,
    "db_generation": 2,
    "is_accredited": 1,
    "_id": "63f788e9b3695239c61b2b0e",
    "state_id": 19,
    "state": "5f0eb6e16dda22674979bf34",
    "lga_id": 3459,
    "ward_id": 21646,
    "state_constituency_id": 467,
    "state_constituency": "5f0f373a93d20b39ceee2187",
    "federal_constituency_id": 155,
    "federal_constituency": "5f0f37fc2d77c83a06f0f3a0",
    "senatorial_district_id": 55,
    "senatorial_district": "5f0f3954970bd83a6f4539eb",
    "name": "UBE UNGWAN NUHU BAKIN GADA",
    "code": "022",
    "pu_code": "18/11/05/022",
    "old_name": "",
    "polling_unit_id": 146912,
    "created_at": "2023-02-23T15:40:25.020Z",
    "updated_at": "2023-02-23T22:08:57.917Z",
    "__v": 0,
    "pu_code_string": "181105022",
    "state_name": "KADUNA",
    "lga_name": "KAGARKO",
    "document": {
      "external": true,
      "status": 1,
      "_id": "6400916a6d4cb40e5f11e547",
      "url": "https://inec-cvr-cache.s3.eu-west-1.amazonaws.com/cached/results/642201/result_115326_1677758822_thumb.jpg",
      "size": 1000,
      "updated_at": "2023-03-02T12:07:06.850Z"
    },
    "old_documents": [],
    "has_old_documents": false
  },
  {
    "status": "ACTIVE",
    "generation": 1,
    "db_generation": 2,
    "is_accredited": 1,
    "_id": "63f788e6b3695239c61b2aaf",
    "state_id": 19,
    "state": "5f0eb6e16dda22674979bf34",
    "lga_id": 3459,
    "ward_id": 21646,
    "state_constituency_id": 467,
    "state_constituency": "5f0f373a93d20b39ceee2187",
    "federal_constituency_id": 155,
    "federal_constituency": "5f0f37fc2d77c83a06f0f3a0",
    "senatorial_district_id": 55,
    "senatorial_district": "5f0f3954970bd83a6f4539eb",
    "name": "UBE PRIMARY SCHOOL TSALLANKIN GIDAN DAN MAI",
    "code": "021",
    "pu_code": "18/11/05/021",
    "old_name": "",
    "polling_unit_id": 146911,
    "created_at": "2023-02-23T15:40:22.951Z",
    "updated_at": "2023-02-23T22:08:57.865Z",
    "__v": 0,
    "pu_code_string": "181105021",
    "state_name": "KADUNA",
    "lga_name": "KAGARKO",
    "document": {
      "external": true,
      "status": 1,
      "_id": "640091666d4cb40e5f11e4e3",
      "url": "https://inec-cvr-cache.s3.eu-west-1.amazonaws.com/cached/results/642200/result_115325_1677758767_thumb.jpg",
      "size": 1000,
      "updated_at": "2023-03-02T12:07:02.904Z"
    },
    "old_documents": [],
    "has_old_documents": false
  },
  {
    "status": "ACTIVE",
    "generation": 1,
    "db_generation": 2,
    "is_accredited": 1,
    "_id": "63f788e4b3695239c61b2a50",
    "state_id": 19,
    "state": "5f0eb6e16dda22674979bf34",
    "lga_id": 3459,
    "ward_id": 21646,
    "state_constituency_id": 467,
    "state_constituency": "5f0f373a93d20b39ceee2187",
    "federal_constituency_id": 155,
    "federal_constituency": "5f0f37fc2d77c83a06f0f3a0",
    "senatorial_district_id": 55,
    "senatorial_district": "5f0f3954970bd83a6f4539eb",
    "name": "PRIMARY HEALTH CENTER MASUKWANI KOFAR ADADA",
    "code": "020",
    "pu_code": "18/11/05/020",
    "old_name": "",
    "polling_unit_id": 146910,
    "created_at": "2023-02-23T15:40:20.857Z",
    "updated_at": "2023-02-23T22:08:57.811Z",
    "__v": 0,
    "pu_code_string": "181105020",
    "state_name": "KADUNA",
    "lga_name": "KAGARKO",
    "document": {
      "external": true,
      "status": 1,
      "_id": "640090f16d4cb40e5f11e4a8",
      "url": "https://inec-cvr-cache.s3.eu-west-1.amazonaws.com/cached/results/642199/result_115324_1677758702_thumb.jpg",
      "size": 1000,
      "updated_at": "2023-03-02T12:05:05.322Z"
    },
    "old_documents": [],
    "has_old_documents": false
  },
  {
    "status": "ACTIVE",
    "generation": 1,
    "db_generation": 2,
    "is_accredited": 1,
    "_id": "63f788e2b3695239c61b29f1",
    "state_id": 19,
    "state": "5f0eb6e16dda22674979bf34",
    "lga_id": 3459,
    "ward_id": 21646,
    "state_constituency_id": 467,
    "state_constituency": "5f0f373a93d20b39ceee2187",
    "federal_constituency_id": 155,
    "federal_constituency": "5f0f37fc2d77c83a06f0f3a0",
    "senatorial_district_id": 55,
    "senatorial_district": "5f0f3954970bd83a6f4539eb",
    "name": "ADULT EDUCATION CENTER CHABIHO/KOFAR DANLATU",
    "code": "019",
    "pu_code": "18/11/05/019",
    "old_name": "",
    "polling_unit_id": 146909,
    "created_at": "2023-02-23T15:40:18.798Z",
    "updated_at": "2023-02-23T22:08:57.756Z",
    "__v": 0,
    "pu_code_string": "181105019",
    "state_name": "KADUNA",
    "lga_name": "KAGARKO",
    "document": {
      "external": true,
      "status": 1,
      "_id": "640090776d4cb40e5f11e3ef",
      "url": "https://inec-cvr-cache.s3.eu-west-1.amazonaws.com/cached/results/642198/result_115323_1677758580_thumb.jpg",
      "size": 1000,
      "updated_at": "2023-03-02T12:03:03.963Z"
    },
    "old_documents": [],
    "has_old_documents": false
  },
  {
    "status": "ACTIVE",
    "generation": 1,
    "db_generation": 2,
    "is_accredited": 1,
    "_id": "63f788e0b3695239c61b2992",
    "state_id": 19,
    "state": "5f0eb6e16dda22674979bf34",
    "lga_id": 3459,
    "ward_id": 21646,
    "state_constituency_id": 467,
    "state_constituency": "5f0f373a93d20b39ceee2187",
    "federal_constituency_id": 155,
    "federal_constituency": "5f0f37fc2d77c83a06f0f3a0",
    "senatorial_district_id": 55,
    "senatorial_district": "5f0f3954970bd83a6f4539eb",
    "name": "SKILL ACQUISITION CENTER UNG. GOBIRAWA",
    "code": "018",
    "pu_code": "18/11/05/018",
    "old_name": "",
    "polling_unit_id": 146908,
    "created_at": "2023-02-23T15:40:16.703Z",
    "updated_at": "2023-02-23T22:08:57.700Z",
    "__v": 0,
    "pu_code_string": "181105018",
    "state_name": "KADUNA",
    "lga_name": "KAGARKO",
    "document": {
      "external": true,
      "status": 1,
      "_id": "6400903b6d4cb40e5f11e37f",
      "url": "https://inec-cvr-cache.s3.eu-west-1.amazonaws.com/cached/results/642197/result_115322_1677758491_thumb.jpg",
      "size": 1000,
      "updated_at": "2023-03-02T12:02:03.239Z"
    },
    "old_documents": [],
    "has_old_documents": false
  },
  {
    "status": "ACTIVE",
    "generation": 1,
    "db_generation": 2,
    "is_accredited": 1,
    "_id": "63f788deb3695239c61b2933",
    "state_id": 19,
    "state": "5f0eb6e16dda22674979bf34",
    "lga_id": 3459,
    "ward_id": 21646,
    "state_constituency_id": 467,
    "state_constituency": "5f0f373a93d20b39ceee2187",
    "federal_constituency_id": 155,
    "federal_constituency": "5f0f37fc2d77c83a06f0f3a0",
    "senatorial_district_id": 55,
    "senatorial_district": "5f0f3954970bd83a6f4539eb",
    "name": "HEALTH CLINIC KOFAR GIDAN AUDIYA UNGWAN IYA",
    "code": "017",
    "pu_code": "18/11/05/017",
    "old_name": "",
    "polling_unit_id": 146907,
    "created_at": "2023-02-23T15:40:14.574Z",
    "updated_at": "2023-02-23T22:08:57.647Z",
    "__v": 0,
    "pu_code_string": "181105017",
    "state_name": "KADUNA",
    "lga_name": "KAGARKO",
    "document": {
      "external": true,
      "status": 1,
      "_id": "64008fc56d4cb40e5f11e30c",
      "url": "https://inec-cvr-cache.s3.eu-west-1.amazonaws.com/cached/results/642196/result_115321_1677758383_thumb.jpg",
      "size": 1000,
      "updated_at": "2023-03-02T12:00:05.106Z"
    },
    "old_documents": [],
    "has_old_documents": false
  },
  {
    "status": "ACTIVE",
    "generation": 1,
    "db_generation": 2,
    "is_accredited": 1,
    "_id": "63f788dcb3695239c61b28d4",
    "state_id": 19,
    "state": "5f0eb6e16dda22674979bf34",
    "lga_id": 3459,
    "ward_id": 21646,
    "state_constituency_id": 467,
    "state_constituency": "5f0f373a93d20b39ceee2187",
    "federal_constituency_id": 155,
    "federal_constituency": "5f0f37fc2d77c83a06f0f3a0",
    "senatorial_district_id": 55,
    "senatorial_district": "5f0f3954970bd83a6f4539eb",
    "name": "SKILL ACQUISITION CENTER GOROH UNG. MAKERA",
    "code": "016",
    "pu_code": "18/11/05/016",
    "old_name": "",
    "polling_unit_id": 146906,
    "created_at": "2023-02-23T15:40:12.521Z",
    "updated_at": "2023-02-23T22:08:57.593Z",
    "__v": 0,
    "pu_code_string": "181105016",
    "state_name": "KADUNA",
    "lga_name": "KAGARKO",
    "document": {
      "external": true,
      "status": 1,
      "_id": "64008f866d4cb40e5f11e272",
      "url": "https://inec-cvr-cache.s3.eu-west-1.amazonaws.com/cached/results/642195/result_115320_1677758301_thumb.jpg",
      "size": 1000,
      "updated_at": "2023-03-02T11:59:02.091Z"
    },
    "old_documents": [],
    "has_old_documents": false
  },
  {
    "status": "ACTIVE",
    "generation": 1,
    "db_generation": 2,
    "is_accredited": 1,
    "_id": "63f788dab3695239c61b2875",
    "state_id": 19,
    "state": "5f0eb6e16dda22674979bf34",
    "lga_id": 3459,
    "ward_id": 21646,
    "state_constituency_id": 467,
    "state_constituency": "5f0f373a93d20b39ceee2187",
    "federal_constituency_id": 155,
    "federal_constituency": "5f0f37fc2d77c83a06f0f3a0",
    "senatorial_district_id": 55,
    "senatorial_district": "5f0f3954970bd83a6f4539eb",
    "name": "PRIMARY HEALTH CENTER FANTARE KOFAR DANGALADIMA",
    "code": "015",
    "pu_code": "18/11/05/015",
    "old_name": "",
    "polling_unit_id": 146905,
    "created_at": "2023-02-23T15:40:10.407Z",
    "updated_at": "2023-02-23T22:08:57.540Z",
    "__v": 0,
    "pu_code_string": "181105015",
    "state_name": "KADUNA",
    "lga_name": "KAGARKO",
    "document": {
      "external": true,
      "status": 1,
      "_id": "64008f4c6d4cb40e5f11e248",
      "url": "https://inec-cvr-cache.s3.eu-west-1.amazonaws.com/cached/results/642194/result_115319_1677758229_thumb.jpg",
      "size": 1000,
      "updated_at": "2023-03-02T11:58:04.111Z"
    },
    "old_documents": [],
    "has_old_documents": false
  },
  {
    "status": "ACTIVE",
    "generation": 1,
    "db_generation": 2,
    "is_accredited": 1,
    "_id": "63f788d8b3695239c61b2816",
    "state_id": 19,
    "state": "5f0eb6e16dda22674979bf34",
    "lga_id": 3459,
    "ward_id": 21646,
    "state_constituency_id": 467,
    "state_constituency": "5f0f373a93d20b39ceee2187",
    "federal_constituency_id": 155,
    "federal_constituency": "5f0f37fc2d77c83a06f0f3a0",
    "senatorial_district_id": 55,
    "senatorial_district": "5f0f3954970bd83a6f4539eb",
    "name": "UBEC GALADANCI KOFAR HAJI",
    "code": "014",
    "pu_code": "18/11/05/014",
    "old_name": "",
    "polling_unit_id": 146904,
    "created_at": "2023-02-23T15:40:08.292Z",
    "updated_at": "2023-02-23T22:08:57.485Z",
    "__v": 0,
    "pu_code_string": "181105014",
    "state_name": "KADUNA",
    "lga_name": "KAGARKO",
    "document": {
      "external": true,
      "status": 1,
      "_id": "64008ed36d4cb40e5f11e170",
      "url": "https://inec-cvr-cache.s3.eu-west-1.amazonaws.com/cached/results/642193/result_115318_1677758136_thumb.jpg",
      "size": 1000,
      "updated_at": "2023-03-02T11:56:03.224Z"
    },
    "old_documents": [],
    "has_old_documents": false
  },
  {
    "status": "ACTIVE",
    "generation": 1,
    "db_generation": 2,
    "is_accredited": 1,
    "_id": "63f788d5b3695239c61b27b7",
    "state_id": 19,
    "state": "5f0eb6e16dda22674979bf34",
    "lga_id": 3459,
    "ward_id": 21646,
    "state_constituency_id": 467,
    "state_constituency": "5f0f373a93d20b39ceee2187",
    "federal_constituency_id": 155,
    "federal_constituency": "5f0f37fc2d77c83a06f0f3a0",
    "senatorial_district_id": 55,
    "senatorial_district": "5f0f3954970bd83a6f4539eb",
    "name": "MOTOR PARK KOFAR MAL SAIDU UNG. KARA",
    "code": "013",
    "pu_code": "18/11/05/013",
    "old_name": "",
    "polling_unit_id": 146903,
    "created_at": "2023-02-23T15:40:05.993Z",
    "updated_at": "2023-02-23T22:08:57.429Z",
    "__v": 0,
    "pu_code_string": "181105013",
    "state_name": "KADUNA",
    "lga_name": "KAGARKO",
    "document": {
      "external": true,
      "status": 1,
      "_id": "64008e976d4cb40e5f11e12c",
      "url": "https://inec-cvr-cache.s3.eu-west-1.amazonaws.com/cached/results/642192/result_115317_1677758048_thumb.jpg",
      "size": 1000,
      "updated_at": "2023-03-02T11:55:03.748Z"
    },
    "old_documents": [],
    "has_old_documents": false
  },
  {
    "status": "ACTIVE",
    "generation": 1,
    "db_generation": 1,
    "is_accredited": 1,
    "_id": "5f0f54ebc440353badb1abfa",
    "state_id": 19,
    "state": "5f0eb6e16dda22674979bf34",
    "lga_id": 3459,
    "ward_id": 21646,
    "state_constituency_id": 467,
    "state_constituency": "5f0f373a93d20b39ceee2187",
    "federal_constituency_id": 155,
    "federal_constituency": "5f0f37fc2d77c83a06f0f3a0",
    "senatorial_district_id": 55,
    "senatorial_district": "5f0f3954970bd83a6f4539eb",
    "name": "GIDAN KARA II/ K/GIDAN MAIANGUWA",
    "code": "012",
    "pu_code": "18/11/05/012",
    "old_name": "",
    "polling_unit_id": 54373,
    "created_at": "2020-07-15T19:11:39.141Z",
    "updated_at": "2023-02-23T20:53:12.277Z",
    "__v": 0,
    "pu_code_string": "181105012",
    "state_name": "KADUNA",
    "lga_name": "KAGARKO",
    "document": {
      "external": true,
      "status": 1,
      "_id": "64008e1e6d4cb40e5f11e06f",
      "url": "https://inec-cvr-cache.s3.eu-west-1.amazonaws.com/cached/results/54282/result_115316_1677757958_thumb.jpg",
      "size": 1000,
      "updated_at": "2023-03-02T11:53:02.773Z"
    },
    "old_documents": [],
    "has_old_documents": false
  },
  {
    "status": "ACTIVE",
    "generation": 1,
    "db_generation": 1,
    "is_accredited": 1,
    "_id": "5f0f54ebc440353badb1abf9",
    "state_id": 19,
    "state": "5f0eb6e16dda22674979bf34",
    "lga_id": 3459,
    "ward_id": 21646,
    "state_constituency_id": 467,
    "state_constituency": "5f0f373a93d20b39ceee2187",
    "federal_constituency_id": 155,
    "federal_constituency": "5f0f37fc2d77c83a06f0f3a0",
    "senatorial_district_id": 55,
    "senatorial_district": "5f0f3954970bd83a6f4539eb",
    "name": "PANA/ K/GIDAN MAIANGUWA",
    "code": "011",
    "pu_code": "18/11/05/011",
    "old_name": "",
    "polling_unit_id": 54372,
    "created_at": "2020-07-15T19:11:39.064Z",
    "updated_at": "2023-02-23T20:53:12.235Z",
    "__v": 0,
    "pu_code_string": "181105011",
    "state_name": "KADUNA",
    "lga_name": "KAGARKO",
    "document": {
      "external": true,
      "status": 1,
      "_id": "64008da96d4cb40e5f11dffe",
      "url": "https://inec-cvr-cache.s3.eu-west-1.amazonaws.com/cached/results/54281/result_115315_1677757860_thumb.jpg",
      "size": 1000,
      "updated_at": "2023-03-02T11:51:05.226Z"
    },
    "old_documents": [],
    "has_old_documents": false
  },
  {
    "status": "ACTIVE",
    "generation": 1,
    "db_generation": 1,
    "is_accredited": 1,
    "_id": "5f0f54ebc440353badb1abf8",
    "state_id": 19,
    "state": "5f0eb6e16dda22674979bf34",
    "lga_id": 3459,
    "ward_id": 21646,
    "state_constituency_id": 467,
    "state_constituency": "5f0f373a93d20b39ceee2187",
    "federal_constituency_id": 155,
    "federal_constituency": "5f0f37fc2d77c83a06f0f3a0",
    "senatorial_district_id": 55,
    "senatorial_district": "5f0f3954970bd83a6f4539eb",
    "name": "IFFE/ L.E.A IFFE",
    "code": "010",
    "pu_code": "18/11/05/010",
    "old_name": "",
    "polling_unit_id": 54371,
    "created_at": "2020-07-15T19:11:39.009Z",
    "updated_at": "2023-02-23T20:53:12.175Z",
    "__v": 0,
    "pu_code_string": "181105010",
    "state_name": "KADUNA",
    "lga_name": "KAGARKO",
    "document": {
      "external": true,
      "status": 1,
      "_id": "64008d6b6d4cb40e5f11df75",
      "url": "https://inec-cvr-cache.s3.eu-west-1.amazonaws.com/cached/results/54280/result_115314_1677757751_thumb.jpg",
      "size": 1000,
      "updated_at": "2023-03-02T11:50:03.265Z"
    },
    "old_documents": [],
    "has_old_documents": false
  },
  {
    "status": "ACTIVE",
    "generation": 1,
    "db_generation": 1,
    "is_accredited": 1,
    "_id": "5f0f54eac440353badb1abf7",
    "state_id": 19,
    "state": "5f0eb6e16dda22674979bf34",
    "lga_id": 3459,
    "ward_id": 21646,
    "state_constituency_id": 467,
    "state_constituency": "5f0f373a93d20b39ceee2187",
    "federal_constituency_id": 155,
    "federal_constituency": "5f0f37fc2d77c83a06f0f3a0",
    "senatorial_district_id": 55,
    "senatorial_district": "5f0f3954970bd83a6f4539eb",
    "name": "MAKERA/ L.E.A. MAKERA",
    "code": "009",
    "pu_code": "18/11/05/009",
    "old_name": "",
    "polling_unit_id": 54370,
    "created_at": "2020-07-15T19:11:38.948Z",
    "updated_at": "2023-02-23T20:53:12.106Z",
    "__v": 0,
    "pu_code_string": "181105009",
    "state_name": "KADUNA",
    "lga_name": "KAGARKO",
    "document": {
      "external": true,
      "status": 1,
      "_id": "64008cf36d4cb40e5f11df02",
      "url": "https://inec-cvr-cache.s3.eu-west-1.amazonaws.com/cached/results/54279/result_115313_1677757638_thumb.jpg",
      "size": 1000,
      "updated_at": "2023-03-02T11:48:03.490Z"
    },
    "old_documents": [],
    "has_old_documents": false
  },
  {
    "status": "ACTIVE",
    "generation": 1,
    "db_generation": 1,
    "is_accredited": 1,
    "_id": "5f0f54eac440353badb1abf6",
    "state_id": 19,
    "state": "5f0eb6e16dda22674979bf34",
    "lga_id": 3459,
    "ward_id": 21646,
    "state_constituency_id": 467,
    "state_constituency": "5f0f373a93d20b39ceee2187",
    "federal_constituency_id": 155,
    "federal_constituency": "5f0f37fc2d77c83a06f0f3a0",
    "senatorial_district_id": 55,
    "senatorial_district": "5f0f3954970bd83a6f4539eb",
    "name": "GIDAN-JIBO/ GIDAN JIBO",
    "code": "008",
    "pu_code": "18/11/05/008",
    "old_name": "",
    "polling_unit_id": 54369,
    "created_at": "2020-07-15T19:11:38.883Z",
    "updated_at": "2023-02-23T20:53:12.048Z",
    "__v": 0,
    "pu_code_string": "181105008",
    "state_name": "KADUNA",
    "lga_name": "KAGARKO",
    "document": {
      "external": true,
      "status": 1,
      "_id": "64008c7c6d4cb40e5f11de6a",
      "url": "https://inec-cvr-cache.s3.eu-west-1.amazonaws.com/cached/results/54278/result_115312_1677757537_thumb.jpg",
      "size": 1000,
      "updated_at": "2023-03-02T11:46:04.699Z"
    },
    "old_documents": [],
    "has_old_documents": false
  },
  {
    "status": "ACTIVE",
    "generation": 1,
    "db_generation": 1,
    "is_accredited": 1,
    "_id": "5f0f54eac440353badb1abf5",
    "state_id": 19,
    "state": "5f0eb6e16dda22674979bf34",
    "lga_id": 3459,
    "ward_id": 21646,
    "state_constituency_id": 467,
    "state_constituency": "5f0f373a93d20b39ceee2187",
    "federal_constituency_id": 155,
    "federal_constituency": "5f0f37fc2d77c83a06f0f3a0",
    "senatorial_district_id": 55,
    "senatorial_district": "5f0f3954970bd83a6f4539eb",
    "name": "MASU - KWANI/ GIDAN M. MOHAMMED",
    "code": "007",
    "pu_code": "18/11/05/007",
    "old_name": "",
    "polling_unit_id": 54368,
    "created_at": "2020-07-15T19:11:38.795Z",
    "updated_at": "2023-02-23T20:53:11.967Z",
    "__v": 0,
    "pu_code_string": "181105007",
    "state_name": "KADUNA",
    "lga_name": "KAGARKO",
    "document": {
      "external": true,
      "status": 1,
      "_id": "64008c046d4cb40e5f11de07",
      "url": "https://inec-cvr-cache.s3.eu-west-1.amazonaws.com/cached/results/54277/result_115311_1677757441_thumb.jpg",
      "size": 1000,
      "updated_at": "2023-03-02T11:44:04.118Z"
    },
    "old_documents": [],
    "has_old_documents": false
  },
  {
    "status": "ACTIVE",
    "generation": 1,
    "db_generation": 1,
    "is_accredited": 1,
    "_id": "5f0f54eac440353badb1abf4",
    "state_id": 19,
    "state": "5f0eb6e16dda22674979bf34",
    "lga_id": 3459,
    "ward_id": 21646,
    "state_constituency_id": 467,
    "state_constituency": "5f0f373a93d20b39ceee2187",
    "federal_constituency_id": 155,
    "federal_constituency": "5f0f37fc2d77c83a06f0f3a0",
    "senatorial_district_id": 55,
    "senatorial_district": "5f0f3954970bd83a6f4539eb",
    "name": "UNG. FADA/ D.H. OFFICE",
    "code": "006",
    "pu_code": "18/11/05/006",
    "old_name": "",
    "polling_unit_id": 54367,
    "created_at": "2020-07-15T19:11:38.728Z",
    "updated_at": "2023-02-23T20:53:11.923Z",
    "__v": 0,
    "pu_code_string": "181105006",
    "state_name": "KADUNA",
    "lga_name": "KAGARKO",
    "document": {
      "external": true,
      "status": 1,
      "_id": "64008bc66d4cb40e5f11dd9c",
      "url": "https://inec-cvr-cache.s3.eu-west-1.amazonaws.com/cached/results/54276/result_115310_1677757343_thumb.jpg",
      "size": 1000,
      "updated_at": "2023-03-02T11:43:02.735Z"
    },
    "old_documents": [],
    "has_old_documents": false
  },
  {
    "status": "ACTIVE",
    "generation": 1,
    "db_generation": 1,
    "is_accredited": 1,
    "_id": "5f0f54eac440353badb1abf3",
    "state_id": 19,
    "state": "5f0eb6e16dda22674979bf34",
    "lga_id": 3459,
    "ward_id": 21646,
    "state_constituency_id": 467,
    "state_constituency": "5f0f373a93d20b39ceee2187",
    "federal_constituency_id": 155,
    "federal_constituency": "5f0f37fc2d77c83a06f0f3a0",
    "senatorial_district_id": 55,
    "senatorial_district": "5f0f3954970bd83a6f4539eb",
    "name": "BAKIN KASUWA/ K/G MAMMAN SHUWA",
    "code": "005",
    "pu_code": "18/11/05/005",
    "old_name": "",
    "polling_unit_id": 54366,
    "created_at": "2020-07-15T19:11:38.662Z",
    "updated_at": "2023-02-23T20:53:11.865Z",
    "__v": 0,
    "pu_code_string": "181105005",
    "state_name": "KADUNA",
    "lga_name": "KAGARKO",
    "document": {
      "external": true,
      "status": 1,
      "_id": "64008b4f6d4cb40e5f11dd1c",
      "url": "https://inec-cvr-cache.s3.eu-west-1.amazonaws.com/cached/results/54275/result_115309_1677757222_thumb.jpg",
      "size": 1000,
      "updated_at": "2023-03-02T11:41:03.052Z"
    },
    "old_documents": [],
    "has_old_documents": false
  },
  {
    "status": "ACTIVE",
    "generation": 1,
    "db_generation": 1,
    "is_accredited": 1,
    "_id": "5f0f54eac440353badb1abf2",
    "state_id": 19,
    "state": "5f0eb6e16dda22674979bf34",
    "lga_id": 3459,
    "ward_id": 21646,
    "state_constituency_id": 467,
    "state_constituency": "5f0f373a93d20b39ceee2187",
    "federal_constituency_id": 155,
    "federal_constituency": "5f0f37fc2d77c83a06f0f3a0",
    "senatorial_district_id": 55,
    "senatorial_district": "5f0f3954970bd83a6f4539eb",
    "name": "DUMALE/ L.E.A. PRI. D/MALE",
    "code": "004",
    "pu_code": "18/11/05/004",
    "old_name": "",
    "polling_unit_id": 54365,
    "created_at": "2020-07-15T19:11:38.590Z",
    "updated_at": "2023-02-23T20:53:11.816Z",
    "__v": 0,
    "pu_code_string": "181105004",
    "state_name": "KADUNA",
    "lga_name": "KAGARKO",
    "document": {
      "external": true,
      "status": 1,
      "_id": "64008ad76d4cb40e5f11dc70",
      "url": "https://inec-cvr-cache.s3.eu-west-1.amazonaws.com/cached/results/54274/result_115308_1677757117_thumb.jpg",
      "size": 1000,
      "updated_at": "2023-03-02T11:39:03.469Z"
    },
    "old_documents": [],
    "has_old_documents": false
  },
  {
    "status": "ACTIVE",
    "generation": 1,
    "db_generation": 1,
    "is_accredited": 1,
    "_id": "5f0f54eac440353badb1abf1",
    "state_id": 19,
    "state": "5f0eb6e16dda22674979bf34",
    "lga_id": 3459,
    "ward_id": 21646,
    "state_constituency_id": 467,
    "state_constituency": "5f0f373a93d20b39ceee2187",
    "federal_constituency_id": 155,
    "federal_constituency": "5f0f37fc2d77c83a06f0f3a0",
    "senatorial_district_id": 55,
    "senatorial_district": "5f0f3954970bd83a6f4539eb",
    "name": "FANTARE/ K/GIDAN DANGALADIMA",
    "code": "003",
    "pu_code": "18/11/05/003",
    "old_name": "",
    "polling_unit_id": 54364,
    "created_at": "2020-07-15T19:11:38.522Z",
    "updated_at": "2023-02-23T20:53:11.727Z",
    "__v": 0,
    "pu_code_string": "181105003",
    "state_name": "KADUNA",
    "lga_name": "KAGARKO",
    "document": {
      "external": true,
      "status": 1,
      "_id": "64008a246d4cb40e5f11dbbf",
      "url": "https://inec-cvr-cache.s3.eu-west-1.amazonaws.com/cached/results/54273/result_115307_1677756921_thumb.jpg",
      "size": 1000,
      "updated_at": "2023-03-02T11:36:04.472Z"
    },
    "old_documents": [],
    "has_old_documents": false
  },
  {
    "status": "ACTIVE",
    "generation": 1,
    "db_generation": 1,
    "is_accredited": 1,
    "_id": "5f0f54eac440353badb1abf0",
    "state_id": 19,
    "state": "5f0eb6e16dda22674979bf34",
    "lga_id": 3459,
    "ward_id": 21646,
    "state_constituency_id": 467,
    "state_constituency": "5f0f373a93d20b39ceee2187",
    "federal_constituency_id": 155,
    "federal_constituency": "5f0f37fc2d77c83a06f0f3a0",
    "senatorial_district_id": 55,
    "senatorial_district": "5f0f3954970bd83a6f4539eb",
    "name": "GALANDACI/ K/GIDAN MAIANGUWA",
    "code": "002",
    "pu_code": "18/11/05/002",
    "old_name": "",
    "polling_unit_id": 54363,
    "created_at": "2020-07-15T19:11:38.457Z",
    "updated_at": "2023-02-23T20:53:11.681Z",
    "__v": 0,
    "pu_code_string": "181105002",
    "state_name": "KADUNA",
    "lga_name": "KAGARKO",
    "document": {
      "external": true,
      "status": 1,
      "_id": "640089ac6d4cb40e5f11db4b",
      "url": "https://inec-cvr-cache.s3.eu-west-1.amazonaws.com/cached/results/54272/result_115306_1677756826_thumb.jpg",
      "size": 1000,
      "updated_at": "2023-03-02T11:34:04.862Z"
    },
    "old_documents": [],
    "has_old_documents": false
  },
  {
    "status": "ACTIVE",
    "generation": 1,
    "db_generation": 1,
    "is_accredited": 1,
    "_id": "5f0f54eac440353badb1abef",
    "state_id": 19,
    "state": "5f0eb6e16dda22674979bf34",
    "lga_id": 3459,
    "ward_id": 21646,
    "state_constituency_id": 467,
    "state_constituency": "5f0f373a93d20b39ceee2187",
    "federal_constituency_id": 155,
    "federal_constituency": "5f0f37fc2d77c83a06f0f3a0",
    "senatorial_district_id": 55,
    "senatorial_district": "5f0f3954970bd83a6f4539eb",
    "name": "GIDAN KARA/ KOFAR SARKI",
    "code": "001",
    "pu_code": "18/11/05/001",
    "old_name": "",
    "polling_unit_id": 54362,
    "created_at": "2020-07-15T19:11:38.393Z",
    "updated_at": "2023-02-23T20:53:11.635Z",
    "__v": 0,
    "pu_code_string": "181105001",
    "state_name": "KADUNA",
    "lga_name": "KAGARKO",
    "document": {
      "external": true,
      "status": 1,
      "_id": "640088f86d4cb40e5f11da29",
      "url": "https://inec-cvr-cache.s3.eu-west-1.amazonaws.com/cached/results/54271/result_115305_1677756654_thumb.jpg",
      "size": 1000,
      "updated_at": "2023-03-02T11:31:04.588Z"
    },
    "old_documents": [],
    "has_old_documents": false
  }
]