[
  {
    "status": "ACTIVE",
    "generation": 1,
    "db_generation": 1,
    "is_accredited": 1,
    "_id": "5f0f595ac440353badb1ebc4",
    "state_id": 22,
    "state": "5f0eb6e16dda22674979bf37",
    "lga_id": 3552,
    "ward_id": 22651,
    "state_constituency_id": 564,
    "state_constituency": "5f0f374093d20b39ceee21e6",
    "federal_constituency_id": 204,
    "federal_constituency": "5f0f37ff2d77c83a06f0f3d1",
    "senatorial_district_id": 122,
    "senatorial_district": "5f0f395a970bd83a6f453a22",
    "name": "KOFAR TUDU",
    "code": "005",
    "pu_code": "21/03/04/005",
    "old_name": "",
    "polling_unit_id": 70701,
    "created_at": "2020-07-15T19:30:34.614Z",
    "updated_at": "2023-02-23T21:08:01.303Z",
    "__v": 0,
    "pu_code_string": "210304005",
    "state_name": "KEBBI",
    "lga_name": "ARGUNGU",
    "ward_name": "GALADIMA",
    "document": {
      "external": false,
      "status": 1,
      "_id": "63fcbb97c4bbf685b44063c1",
      "url": "https://docs.inecelectionresults.net/elections_prod/1292/state/1/lga/3552/ward/22651/pu/70701/70701-1677507432.pdf",
      "size": 3067862,
      "updated_at": "2023-02-27T14:17:59.956Z"
    },
    "old_documents": [],
    "has_old_documents": false
  },
  {
    "status": "ACTIVE",
    "generation": 1,
    "db_generation": 1,
    "is_accredited": 1,
    "_id": "5f0f595ac440353badb1ebc2",
    "state_id": 22,
    "state": "5f0eb6e16dda22674979bf37",
    "lga_id": 3552,
    "ward_id": 22651,
    "state_constituency_id": 564,
    "state_constituency": "5f0f374093d20b39ceee21e6",
    "federal_constituency_id": 204,
    "federal_constituency": "5f0f37ff2d77c83a06f0f3d1",
    "senatorial_district_id": 122,
    "senatorial_district": "5f0f395a970bd83a6f453a22",
    "name": "KABANCHI DISPLAY AREA",
    "code": "003",
    "pu_code": "21/03/04/003",
    "old_name": "",
    "polling_unit_id": 70699,
    "created_at": "2020-07-15T19:30:34.260Z",
    "updated_at": "2023-02-23T21:08:01.225Z",
    "__v": 0,
    "pu_code_string": "210304003",
    "state_name": "KEBBI",
    "lga_name": "ARGUNGU",
    "ward_name": "GALADIMA",
    "document": {
      "external": false,
      "status": 1,
      "_id": "63fcb5438ae66583f6d18f08",
      "url": "https://docs.inecelectionresults.net/elections_prod/1292/state/1/lga/3552/ward/22651/pu/70699/70699-1677505798.pdf",
      "size": 2972646,
      "updated_at": "2023-02-27T13:50:59.836Z"
    },
    "old_documents": [],
    "has_old_documents": false
  },
  {
    "status": "ACTIVE",
    "generation": 1,
    "db_generation": 2,
    "is_accredited": 1,
    "_id": "63f78e41b3695239c61c08f9",
    "state_id": 22,
    "state": "5f0eb6e16dda22674979bf37",
    "lga_id": 3552,
    "ward_id": 22651,
    "state_constituency_id": 564,
    "state_constituency": "5f0f374093d20b39ceee21e6",
    "federal_constituency_id": 204,
    "federal_constituency": "5f0f37ff2d77c83a06f0f3d1",
    "senatorial_district_id": 122,
    "senatorial_district": "5f0f395a970bd83a6f453a22",
    "name": "KOFAR TUDU / MERAWA",
    "code": "011",
    "pu_code": "21/03/04/011",
    "old_name": "",
    "polling_unit_id": 153163,
    "created_at": "2023-02-23T16:03:13.456Z",
    "updated_at": "2023-02-23T22:15:48.740Z",
    "__v": 0,
    "pu_code_string": "210304011",
    "state_name": "KEBBI",
    "lga_name": "ARGUNGU",
    "ward_name": "GALADIMA",
    "document": {
      "external": false,
      "status": 1,
      "_id": "63fcb3a71172578357f57496",
      "url": "https://docs.inecelectionresults.net/elections_prod/1292/state/1/lga/3552/ward/22651/pu/153163/153163-1677505106.pdf",
      "size": 2445207,
      "updated_at": "2023-02-27T13:44:07.669Z"
    },
    "old_documents": [],
    "has_old_documents": false
  },
  {
    "status": "ACTIVE",
    "generation": 1,
    "db_generation": 1,
    "is_accredited": 1,
    "_id": "5f0f595ac440353badb1ebc3",
    "state_id": 22,
    "state": "5f0eb6e16dda22674979bf37",
    "lga_id": 3552,
    "ward_id": 22651,
    "state_constituency_id": 564,
    "state_constituency": "5f0f374093d20b39ceee21e6",
    "federal_constituency_id": 204,
    "federal_constituency": "5f0f37ff2d77c83a06f0f3d1",
    "senatorial_district_id": 122,
    "senatorial_district": "5f0f395a970bd83a6f453a22",
    "name": "MARINAR KAURA",
    "code": "004",
    "pu_code": "21/03/04/004",
    "old_name": "MARINA KAURA",
    "polling_unit_id": 70700,
    "created_at": "2020-07-15T19:30:34.438Z",
    "updated_at": "2023-02-23T21:08:01.267Z",
    "__v": 0,
    "pu_code_string": "210304004",
    "state_name": "KEBBI",
    "lga_name": "ARGUNGU",
    "ward_name": "GALADIMA",
    "document": {
      "external": false,
      "status": 1,
      "_id": "63fcafa5cb676b820ad5e459",
      "url": "https://docs.inecelectionresults.net/elections_prod/1292/state/1/lga/3552/ward/22651/pu/70700/70700-1677504404.pdf",
      "size": 4773543,
      "updated_at": "2023-02-27T13:27:01.393Z"
    },
    "old_documents": [],
    "has_old_documents": false
  },
  {
    "status": "ACTIVE",
    "generation": 1,
    "db_generation": 2,
    "is_accredited": 1,
    "_id": "63f78e3db3695239c61c0845",
    "state_id": 22,
    "state": "5f0eb6e16dda22674979bf37",
    "lga_id": 3552,
    "ward_id": 22651,
    "state_constituency_id": 564,
    "state_constituency": "5f0f374093d20b39ceee21e6",
    "federal_constituency_id": 204,
    "federal_constituency": "5f0f37ff2d77c83a06f0f3d1",
    "senatorial_district_id": 122,
    "senatorial_district": "5f0f395a970bd83a6f453a22",
    "name": "BARIKIN GARI/ YAN LEMU",
    "code": "007",
    "pu_code": "21/03/04/007",
    "old_name": "",
    "polling_unit_id": 153159,
    "created_at": "2023-02-23T16:03:09.927Z",
    "updated_at": "2023-02-23T22:15:48.562Z",
    "__v": 0,
    "pu_code_string": "210304007",
    "state_name": "KEBBI",
    "lga_name": "ARGUNGU",
    "ward_name": "GALADIMA",
    "document": {
      "external": false,
      "status": 1,
      "_id": "63fcad0fd19e4b810726114b",
      "url": "https://docs.inecelectionresults.net/elections_prod/1292/state/1/lga/3552/ward/22651/pu/153159/153159-1677503698.pdf",
      "size": 3154099,
      "updated_at": "2023-02-27T13:15:59.893Z"
    },
    "old_documents": [],
    "has_old_documents": false
  },
  {
    "status": "ACTIVE",
    "generation": 1,
    "db_generation": 2,
    "is_accredited": 1,
    "_id": "63f78e3eb3695239c61c0872",
    "state_id": 22,
    "state": "5f0eb6e16dda22674979bf37",
    "lga_id": 3552,
    "ward_id": 22651,
    "state_constituency_id": 564,
    "state_constituency": "5f0f374093d20b39ceee21e6",
    "federal_constituency_id": 204,
    "federal_constituency": "5f0f37ff2d77c83a06f0f3d1",
    "senatorial_district_id": 122,
    "senatorial_district": "5f0f395a970bd83a6f453a22",
    "name": "MERAWA/RIJIYAR KUNGIYA",
    "code": "008",
    "pu_code": "21/03/04/008",
    "old_name": "",
    "polling_unit_id": 153160,
    "created_at": "2023-02-23T16:03:10.790Z",
    "updated_at": "2023-02-23T22:15:48.609Z",
    "__v": 0,
    "pu_code_string": "210304008",
    "state_name": "KEBBI",
    "lga_name": "ARGUNGU",
    "ward_name": "GALADIMA",
    "document": {
      "external": false,
      "status": 1,
      "_id": "63fca98eef02be7f3b5c1fb2",
      "url": "https://docs.inecelectionresults.net/elections_prod/1292/state/1/lga/3552/ward/22651/pu/153160/153160-1677502826.pdf",
      "size": 4696356,
      "updated_at": "2023-02-27T13:01:02.279Z"
    },
    "old_documents": [],
    "has_old_documents": false
  },
  {
    "status": "ACTIVE",
    "generation": 1,
    "db_generation": 2,
    "is_accredited": 1,
    "_id": "63f78e42b3695239c61c0926",
    "state_id": 22,
    "state": "5f0eb6e16dda22674979bf37",
    "lga_id": 3552,
    "ward_id": 22651,
    "state_constituency_id": 564,
    "state_constituency": "5f0f374093d20b39ceee21e6",
    "federal_constituency_id": 204,
    "federal_constituency": "5f0f37ff2d77c83a06f0f3d1",
    "senatorial_district_id": 122,
    "senatorial_district": "5f0f395a970bd83a6f453a22",
    "name": "MARINAR KAURA/ BAKIN RUWA",
    "code": "012",
    "pu_code": "21/03/04/012",
    "old_name": "",
    "polling_unit_id": 153164,
    "created_at": "2023-02-23T16:03:14.303Z",
    "updated_at": "2023-02-23T22:15:48.786Z",
    "__v": 0,
    "pu_code_string": "210304012",
    "state_name": "KEBBI",
    "lga_name": "ARGUNGU",
    "ward_name": "GALADIMA",
    "document": {
      "external": false,
      "status": 1,
      "_id": "63fca7e9ef02be7f3b5c1838",
      "url": "https://docs.inecelectionresults.net/elections_prod/1292/state/1/lga/3552/ward/22651/pu/153164/153164-1677502384.pdf",
      "size": 3348918,
      "updated_at": "2023-02-27T12:54:01.257Z"
    },
    "old_documents": [],
    "has_old_documents": false
  },
  {
    "status": "ACTIVE",
    "generation": 1,
    "db_generation": 1,
    "is_accredited": 1,
    "_id": "5f0f595ac440353badb1ebc5",
    "state_id": 22,
    "state": "5f0eb6e16dda22674979bf37",
    "lga_id": 3552,
    "ward_id": 22651,
    "state_constituency_id": 564,
    "state_constituency": "5f0f374093d20b39ceee21e6",
    "federal_constituency_id": 204,
    "federal_constituency": "5f0f37ff2d77c83a06f0f3d1",
    "senatorial_district_id": 122,
    "senatorial_district": "5f0f395a970bd83a6f453a22",
    "name": "FORESTRY I AREA",
    "code": "006",
    "pu_code": "21/03/04/006",
    "old_name": "",
    "polling_unit_id": 70702,
    "created_at": "2020-07-15T19:30:34.791Z",
    "updated_at": "2023-02-23T21:08:01.339Z",
    "__v": 0,
    "pu_code_string": "210304006",
    "state_name": "KEBBI",
    "lga_name": "ARGUNGU",
    "ward_name": "GALADIMA",
    "document": {
      "external": false,
      "status": 1,
      "_id": "63fca3b1ef02be7f3b5c049b",
      "url": "https://docs.inecelectionresults.net/elections_prod/1292/state/1/lga/3552/ward/22651/pu/70702/70702-1677501316.pdf",
      "size": 5896678,
      "updated_at": "2023-02-27T12:36:01.438Z"
    },
    "old_documents": [],
    "has_old_documents": false
  },
  {
    "status": "ACTIVE",
    "generation": 1,
    "db_generation": 2,
    "is_accredited": 1,
    "_id": "63f78e44b3695239c61c0980",
    "state_id": 22,
    "state": "5f0eb6e16dda22674979bf37",
    "lga_id": 3552,
    "ward_id": 22651,
    "state_constituency_id": 564,
    "state_constituency": "5f0f374093d20b39ceee21e6",
    "federal_constituency_id": 204,
    "federal_constituency": "5f0f37ff2d77c83a06f0f3d1",
    "senatorial_district_id": 122,
    "senatorial_district": "5f0f395a970bd83a6f453a22",
    "name": "KABANCHI/DAN DURUMI",
    "code": "014",
    "pu_code": "21/03/04/014",
    "old_name": "",
    "polling_unit_id": 153166,
    "created_at": "2023-02-23T16:03:16.087Z",
    "updated_at": "2023-02-23T22:15:48.900Z",
    "__v": 0,
    "pu_code_string": "210304014",
    "state_name": "KEBBI",
    "lga_name": "ARGUNGU",
    "ward_name": "GALADIMA",
    "document": {
      "external": false,
      "status": 1,
      "_id": "63fca02c6c0a647da3890930",
      "url": "https://docs.inecelectionresults.net/elections_prod/1292/state/1/lga/3552/ward/22651/pu/153166/153166-1677500406.pdf",
      "size": 3376694,
      "updated_at": "2023-02-27T12:21:00.984Z"
    },
    "old_documents": [],
    "has_old_documents": false
  },
  {
    "status": "ACTIVE",
    "generation": 1,
    "db_generation": 2,
    "is_accredited": 1,
    "_id": "63f78e43b3695239c61c0953",
    "state_id": 22,
    "state": "5f0eb6e16dda22674979bf37",
    "lga_id": 3552,
    "ward_id": 22651,
    "state_constituency_id": 564,
    "state_constituency": "5f0f374093d20b39ceee21e6",
    "federal_constituency_id": 204,
    "federal_constituency": "5f0f37ff2d77c83a06f0f3d1",
    "senatorial_district_id": 122,
    "senatorial_district": "5f0f395a970bd83a6f453a22",
    "name": "BAKIN GARI 2/ GARKAR SARAKI",
    "code": "013",
    "pu_code": "21/03/04/013",
    "old_name": "",
    "polling_unit_id": 153165,
    "created_at": "2023-02-23T16:03:15.190Z",
    "updated_at": "2023-02-23T22:15:48.840Z",
    "__v": 0,
    "pu_code_string": "210304013",
    "state_name": "KEBBI",
    "lga_name": "ARGUNGU",
    "ward_name": "GALADIMA",
    "document": {
      "external": false,
      "status": 1,
      "_id": "63fc9f006c0a647da38903f1",
      "url": "https://docs.inecelectionresults.net/elections_prod/1292/state/1/lga/3552/ward/22651/pu/153165/153165-1677500102.pdf",
      "size": 5171761,
      "updated_at": "2023-02-27T12:16:00.963Z"
    },
    "old_documents": [],
    "has_old_documents": false
  },
  {
    "status": "ACTIVE",
    "generation": 1,
    "db_generation": 1,
    "is_accredited": 1,
    "_id": "5f0f595ac440353badb1ebc1",
    "state_id": 22,
    "state": "5f0eb6e16dda22674979bf37",
    "lga_id": 3552,
    "ward_id": 22651,
    "state_constituency_id": 564,
    "state_constituency": "5f0f374093d20b39ceee21e6",
    "federal_constituency_id": 204,
    "federal_constituency": "5f0f37ff2d77c83a06f0f3d1",
    "senatorial_district_id": 122,
    "senatorial_district": "5f0f395a970bd83a6f453a22",
    "name": "BARIKIN GARI",
    "code": "002",
    "pu_code": "21/03/04/002",
    "old_name": "",
    "polling_unit_id": 70698,
    "created_at": "2020-07-15T19:30:34.089Z",
    "updated_at": "2023-02-23T21:08:01.184Z",
    "__v": 0,
    "pu_code_string": "210304002",
    "state_name": "KEBBI",
    "lga_name": "ARGUNGU",
    "ward_name": "GALADIMA",
    "document": {
      "external": false,
      "status": 1,
      "_id": "63fc9c316c0a647da388f6bb",
      "url": "https://docs.inecelectionresults.net/elections_prod/1292/state/1/lga/3552/ward/22651/pu/70698/70698-1677499409.pdf",
      "size": 5105391,
      "updated_at": "2023-02-27T12:04:01.133Z"
    },
    "old_documents": [],
    "has_old_documents": false
  },
  {
    "status": "ACTIVE",
    "generation": 1,
    "db_generation": 1,
    "is_accredited": 1,
    "_id": "5f0f5959c440353badb1ebc0",
    "state_id": 22,
    "state": "5f0eb6e16dda22674979bf37",
    "lga_id": 3552,
    "ward_id": 22651,
    "state_constituency_id": 564,
    "state_constituency": "5f0f374093d20b39ceee21e6",
    "federal_constituency_id": 204,
    "federal_constituency": "5f0f37ff2d77c83a06f0f3d1",
    "senatorial_district_id": 122,
    "senatorial_district": "5f0f395a970bd83a6f453a22",
    "name": "OLD POST OFFICE",
    "code": "001",
    "pu_code": "21/03/04/001",
    "old_name": "",
    "polling_unit_id": 70697,
    "created_at": "2020-07-15T19:30:33.911Z",
    "updated_at": "2023-02-23T21:08:01.141Z",
    "__v": 0,
    "pu_code_string": "210304001",
    "state_name": "KEBBI",
    "lga_name": "ARGUNGU",
    "ward_name": "GALADIMA",
    "document": {
      "external": false,
      "status": 1,
      "_id": "63fc9871b605c77c343fd8c0",
      "url": "https://docs.inecelectionresults.net/elections_prod/1292/state/1/lga/3552/ward/22651/pu/70697/70697-1677498444.pdf",
      "size": 2791729,
      "updated_at": "2023-02-27T11:48:01.406Z"
    },
    "old_documents": [],
    "has_old_documents": false
  },
  {
    "status": "ACTIVE",
    "generation": 1,
    "db_generation": 2,
    "is_accredited": 1,
    "_id": "63f78e40b3695239c61c08cc",
    "state_id": 22,
    "state": "5f0eb6e16dda22674979bf37",
    "lga_id": 3552,
    "ward_id": 22651,
    "state_constituency_id": 564,
    "state_constituency": "5f0f374093d20b39ceee21e6",
    "federal_constituency_id": 204,
    "federal_constituency": "5f0f37ff2d77c83a06f0f3d1",
    "senatorial_district_id": 122,
    "senatorial_district": "5f0f395a970bd83a6f453a22",
    "name": "YARI BAGAYA",
    "code": "010",
    "pu_code": "21/03/04/010",
    "old_name": "",
    "polling_unit_id": 153162,
    "created_at": "2023-02-23T16:03:12.598Z",
    "updated_at": "2023-02-23T22:15:48.699Z",
    "__v": 0,
    "pu_code_string": "210304010",
    "state_name": "KEBBI",
    "lga_name": "ARGUNGU",
    "ward_name": "GALADIMA",
    "document": {
      "external": false,
      "status": 1,
      "_id": "63fc91df25ebda77e8451371",
      "url": "https://docs.inecelectionresults.net/elections_prod/1292/state/1/lga/3552/ward/22651/pu/153162/153162-1677496747.pdf",
      "size": 4184503,
      "updated_at": "2023-02-27T11:19:59.969Z"
    },
    "old_documents": [],
    "has_old_documents": false
  },
  {
    "status": "ACTIVE",
    "generation": 1,
    "db_generation": 2,
    "is_accredited": 1,
    "_id": "63f78e3fb3695239c61c089f",
    "state_id": 22,
    "state": "5f0eb6e16dda22674979bf37",
    "lga_id": 3552,
    "ward_id": 22651,
    "state_constituency_id": 564,
    "state_constituency": "5f0f374093d20b39ceee21e6",
    "federal_constituency_id": 204,
    "federal_constituency": "5f0f37ff2d77c83a06f0f3d1",
    "senatorial_district_id": 122,
    "senatorial_district": "5f0f395a970bd83a6f453a22",
    "name": "MERAWA WURIYA",
    "code": "009",
    "pu_code": "21/03/04/009",
    "old_name": "",
    "polling_unit_id": 153161,
    "created_at": "2023-02-23T16:03:11.685Z",
    "updated_at": "2023-02-23T22:15:48.653Z",
    "__v": 0,
    "pu_code_string": "210304009",
    "state_name": "KEBBI",
    "lga_name": "ARGUNGU",
    "ward_name": "GALADIMA",
    "document": {
      "external": false,
      "status": 1,
      "_id": "63fb86af84f1dc4310654011",
      "url": "https://docs.inecelectionresults.net/elections_prod/1292/state/01/lga/03/ward/04/pu/009/009-1677428339.pdf",
      "size": 3489576,
      "updated_at": "2023-02-26T16:19:59.742Z"
    },
    "old_documents": [],
    "has_old_documents": false
  },
  {
    "status": "ACTIVE",
    "generation": 1,
    "db_generation": 2,
    "is_accredited": 1,
    "_id": "63f78e45b3695239c61c09ad",
    "state_id": 22,
    "state": "5f0eb6e16dda22674979bf37",
    "lga_id": 3552,
    "ward_id": 22651,
    "state_constituency_id": 564,
    "state_constituency": "5f0f374093d20b39ceee21e6",
    "federal_constituency_id": 204,
    "federal_constituency": "5f0f37ff2d77c83a06f0f3d1",
    "senatorial_district_id": 122,
    "senatorial_district": "5f0f395a970bd83a6f453a22",
    "name": "KANTA MUSEUM",
    "code": "015",
    "pu_code": "21/03/04/015",
    "old_name": "",
    "polling_unit_id": 153167,
    "created_at": "2023-02-23T16:03:17.034Z",
    "updated_at": "2023-02-23T22:15:48.966Z",
    "__v": 0,
    "pu_code_string": "210304015",
    "state_name": "KEBBI",
    "lga_name": "ARGUNGU",
    "ward_name": "GALADIMA",
    "document": {
      "external": false,
      "status": 1,
      "_id": "63fa79ea5a3dda0199df655e",
      "url": "https://docs.inecelectionresults.net/elections_prod/1292/state/01/lga/03/ward/04/pu/015/015-1677358654.pdf",
      "size": 80256,
      "updated_at": "2023-02-25T21:13:14.419Z"
    },
    "old_documents": [],
    "has_old_documents": false
  }
]